<?xml version="1.0" encoding="utf-8" ?><dwsync><file name="index.php" server="45.63.100.95//public_html/wp-content/themes/winston/" local="3668067390" remote="3668067391" Dst="-1" /><file name="style.css" server="45.63.100.95//public_html/wp-content/themes/winston/" local="3668176377" remote="3668176386" Dst="-1" /><file name="header.php" server="45.63.100.95//public_html/wp-content/themes/winston/" local="3668168116" remote="3668168117" Dst="-1" /><file name="home.php" server="45.63.100.95//public_html/wp-content/themes/winston/" local="3668090828" remote="3668090829" Dst="-1" /><file name="footer.php" server="45.63.100.95//public_html/wp-content/themes/winston/" local="3668167826" remote="3668167828" Dst="-1" /><file name="404.php" server="45.63.100.95//public_html/wp-content/themes/winston/" local="3668168093" remote="3668168095" Dst="-1" /><file name="single.php" server="45.63.100.95//public_html/wp-content/themes/winston/" local="3668168355" remote="3668168356" Dst="-1" /><file name="single-event.php" server="45.63.100.95//public_html/wp-content/themes/winston/" local="3668177292" remote="3668177293" Dst="-1" /><file name="functions.php" server="45.63.100.95//public_html/wp-content/themes/winston/" local="3668177342" remote="3668177343" Dst="-1" /></dwsync>